Metadata-Version: 2.1
Name: soda-core-duckdb
Version: 3.5.6
License-File: LICENSE
Requires-Dist: soda-core==3.5.6
Requires-Dist: duckdb<1.1.0
